waterfall/WatermarkerBase.py
waterfall/WatermarkingFn.py
waterfall/WatermarkingFnFourier.py
waterfall/WatermarkingFnSquare.py
waterfall/__init__.py
waterfall/permute.py
waterfall/watermark.py
waterfall-0.2.12.dist-info/METADATA
waterfall-0.2.12.dist-info/WHEEL
waterfall-0.2.12.dist-info/entry_points.txt
waterfall-0.2.12.dist-info/licenses/LICENSE
waterfall-0.2.12.dist-info/RECORD
