Metadata-Version: 2.4
Name: waterfall
Version: 0.2.12
Summary: Scalable Framework for Robust Text Watermarking and Provenance for LLMs
Project-URL: Homepage, https://github.com/aoi3142/Waterfall
Project-URL: Issues, https://github.com/aoi3142/Waterfall/issues
Author-email: Xinyuan Niu <aperture@outlook.sg>
License-Expression: Apache-2.0
License-File: LICENSE
Classifier: Operating System :: OS Independent
Classifier: Programming Language :: Python :: 3
Requires-Python: >=3.10
Requires-Dist: accelerate>=0.29.0
Requires-Dist: numpy>=1.25.0
Requires-Dist: scipy>=1.13.0
Requires-Dist: sentence-transformers>=3.0.0
Requires-Dist: torch>=2.3.0
Requires-Dist: transformers>=4.43.1
